bioat/__init__.py
bioat/__main__.py
bioat/_meta.py
bioat/about.py
bioat/bamtools.py
bioat/bedtools.py
bioat/cli.py
bioat/crisprtools.py
bioat/devtools.py
bioat/exceptions.py
bioat/fastxtools.py
bioat/foldtools.py
bioat/hictools.py
bioat/lib/3Dmol-min.js
bioat/lib/__init__.py
bioat/lib/circos/example_data_barplot.csv
bioat/lib/circos/example_data_chromosome_cytoband.csv
bioat/lib/circos/example_data_chromosome_general.csv
bioat/lib/circos/example_data_links.csv
bioat/lib/circos/example_data_point.csv
bioat/lib/circos/example_data_rect_gradual.csv
bioat/lib/circos/hg38_chromosome_length.csv
bioat/lib/circos/hg38_cytoBand.csv
bioat/lib/circos/mm10_chromosome_length.csv
bioat/lib/circos/mm10_cytoBand.csv
bioat/lib/libalignment.py
bioat/lib/libcircos.py
bioat/lib/libcolor.py
bioat/lib/libcrispr.py
bioat/lib/libdataclasses.py
bioat/lib/libdetect_seq.py
bioat/lib/libfastx.py
bioat/lib/libjgi.py
bioat/lib/libjupyter.py
bioat/lib/libpandas.py
bioat/lib/libpatentseq.py
bioat/lib/libpath.py
bioat/lib/libpdb.py
bioat/lib/libphylo.py
bioat/lib/libplot/Helvetica-Bold.ttf
bioat/lib/libplot/Helvetica-BoldOblique.ttf
bioat/lib/libplot/Helvetica-Light.ttf
bioat/lib/libplot/Helvetica-Oblique.ttf
bioat/lib/libplot/Helvetica.ttf
bioat/lib/libplot.py
bioat/lib/libsnakemake.py
bioat/lib/libspider.py
bioat/lib/patentseq/font-awesome.min.css
bioat/lib/patentseq/index.css
bioat/lib/patentseq/psf-ui.4.0-overide.min.css
bioat/logger.py
bioat/metatools.py
bioat/searchtools.py
bioat/systemtools.py
bioat/tabletools.py
bioat/target_seq.py
bioat-0.16.4.dist-info/METADATA
bioat-0.16.4.dist-info/WHEEL
bioat-0.16.4.dist-info/entry_points.txt
bioat-0.16.4.dist-info/licenses/LICENSE
bioat-0.16.4.dist-info/RECORD
