Metadata-Version: 2.4
Name: bioat
Version: 0.16.4
Summary: bioat, a python package & command line toolkit for Bioinformatics and data science!
License: Apache-2.0
License-File: LICENSE
Keywords: bioat,bioinformatics,data science,deep learning
Author: Huanan Herman Zhao
Author-email: hermanzhaozzzz@gmail.com
Maintainer: Huanan Herman Zhao
Maintainer-email: hermanzhaozzzz@gmail.com
Requires-Python: >=3.10.0,<4.0
Classifier: Development Status :: 4 - Beta
Classifier: Intended Audience :: Developers
Classifier: Intended Audience :: Science/Research
Classifier: License :: OSI Approved :: Apache Software License
Classifier: Programming Language :: Python :: 3.10
Classifier: Programming Language :: Python :: 3.11
Classifier: Programming Language :: Python :: 3.12
Classifier: Programming Language :: Python :: 3.13
Classifier: Topic :: Scientific/Engineering :: Artificial Intelligence
Classifier: Topic :: Scientific/Engineering :: Bio-Informatics
Classifier: Topic :: Scientific/Engineering :: Medical Science Apps.
Classifier: Topic :: Scientific/Engineering :: Visualization
Classifier: Topic :: Software Development :: Libraries :: Python Modules
Classifier: Topic :: Utilities
Provides-Extra: dev
Provides-Extra: docs
Provides-Extra: test
Requires-Dist: beautifulsoup4 (>=4.12.3)
Requires-Dist: biopython (>=1.80)
Requires-Dist: coloredlogs (>=15.0.1)
Requires-Dist: fire (>=0.5.0)
Requires-Dist: ipykernel (>=6.0.0)
Requires-Dist: ipython (<9.0.0)
Requires-Dist: matplotlib (>=3.5.3)
Requires-Dist: matplotlib-inline (>=0.1.7)
Requires-Dist: myst-parser ; extra == "docs"
Requires-Dist: numpy (>=1.24.1)
Requires-Dist: openpyxl (>=3.1.2)
Requires-Dist: pandas (>=1.5)
Requires-Dist: psutil (>=5.9.8)
Requires-Dist: py3dmol (>=2.4.2)
Requires-Dist: pytest ; extra == "test"
Requires-Dist: pytest-cov ; extra == "test"
Requires-Dist: requests (>=2.31.0)
Requires-Dist: ruff ; extra == "dev"
Requires-Dist: scikit-learn (>=1.0.2)
Requires-Dist: scipy (>=1.7.3)
Requires-Dist: seaborn (>=0.13.2)
Requires-Dist: selenium (>=4.1.3)
Requires-Dist: sphinx ; extra == "docs"
Requires-Dist: sphinx-autobuild ; extra == "docs"
Requires-Dist: sphinx-rtd-theme ; extra == "docs"
Requires-Dist: statsmodels (>=0.13.5)
Requires-Dist: tabulate (>=0.9.0)
Requires-Dist: toml ; extra == "dev"
Requires-Dist: tqdm (>=4.64.1)
Project-URL: Bug Tracker, https://github.com/hermanzhaozzzz/bioat/issues
Project-URL: Documentation, https://bioat.readthedocs.io/en/latest/
Project-URL: Homepage, https://github.com/hermanzhaozzzz/bioat
Project-URL: Repository, https://github.com/hermanzhaozzzz/bioat
